{
  "version": 1,
  "width": 132,
  "height": 34,
  "duration": 97.843509,
  "command": "/bin/bash",
  "title": "",
  "env": {
    "TERM": "xterm-256color",
    "SHELL": "/bin/bash"
  },
  "stdout": [
    [
      0.021954,
      "\u001b[?1034h"
    ],
    [
      0.000025,
      "bash-3.2$ "
    ],
    [
      7.068263,
      "\r\u001b[Kbash-3.2$ "
    ],
    [
      0.021643,
      "\r\u001b[Kbash-3.2$ "
    ],
    [
      0.030762,
      "\r\u001b[Kbash-3.2$ "
    ],
    [
      0.051933,
      "\r\u001b[Kbash-3.2$ "
    ],
    [
      0.052244,
      "\r\u001b[Kbash-3.2$ "
    ],
    [
      0.281587,
      "\r\u001b[Kbash-3.2$ "
    ],
    [
      0.053324,
      "\r\u001b[Kbash-3.2$ "
    ],
    [
      0.018268,
      "\r\u001b[Kbash-3.2$ "
    ],
    [
      0.026497,
      "\r\u001b[Kbash-3.2$ "
    ],
    [
      0.022876,
      "\r\u001b[Kbash-3.2$ "
    ],
    [
      0.916646,
      "\r\u001b[Kbash-3.2$ "
    ],
    [
      0.017388,
      "\r\u001b[Kbash-3.2$ "
    ],
    [
      0.033355,
      "\r\u001b[Kbash-3.2$ "
    ],
    [
      0.463822,
      "\r\u001b[Kbash-3.2$ "
    ],
    [
      0.035801,
      "\r\u001b[Kbash-3.2$ "
    ],
    [
      22.595700,
      "l"
    ],
    [
      0.019709,
      "s"
    ],
    [
      0.077528,
      " "
    ],
    [
      0.080041,
      "-"
    ],
    [
      0.122508,
      "l"
    ],
    [
      0.042875,
      "a"
    ],
    [
      0.114624,
      "\r\n"
    ],
    [
      0.003812,
      "total 0\r\n"
    ],
    [
      0.000155,
      "drwxr-xr-x   4 tikim  staff  136 Apr 20 17:27 .\r\n"
    ],
    [
      0.000006,
      "drwxr-xr-x   6 tikim  staff  204 Apr 20 16:33 ..\r\ndrwxr-xr-x  19 tikim  staff  646 Apr 20 17:27 bi_dashboard\r\n"
    ],
    [
      0.000004,
      "drwxr-xr-x  17 tikim  staff  578 Feb  2 18:07 nginx-1.8.1\r\n"
    ],
    [
      0.000372,
      "bash-3.2$ "
    ],
    [
      9.225783,
      "b"
    ],
    [
      0.101313,
      "o"
    ],
    [
      0.123992,
      "o"
    ],
    [
      0.247456,
      "2"
    ],
    [
      0.562566,
      "\u0008\u001b[K"
    ],
    [
      0.134685,
      "t"
    ],
    [
      0.292749,
      "2"
    ],
    [
      7.076087,
      "d"
    ],
    [
      0.089921,
      "o"
    ],
    [
      0.067665,
      "c"
    ],
    [
      0.101333,
      "k"
    ],
    [
      0.078708,
      "e"
    ],
    [
      0.078788,
      "r"
    ],
    [
      1.732535,
      "\r\n"
    ],
    [
      0.060251,
      "Usage: boot2docker [\u003coptions\u003e] {help|init|up|ssh|save|down|poweroff|reset|restart|config|status|info|ip|shellinit|delete|download|upgrade|version} [\u003cargs\u003e]\r\n"
    ],
    [
      0.000767,
      "bash-3.2$ "
    ],
    [
      1.424081,
      "boot2docker"
    ],
    [
      0.472391,
      " "
    ],
    [
      0.134776,
      "s"
    ],
    [
      0.112710,
      "t"
    ],
    [
      0.101182,
      "a"
    ],
    [
      0.056039,
      "t"
    ],
    [
      0.123773,
      "y"
    ],
    [
      0.630356,
      "\u0008\u001b[K"
    ],
    [
      0.191229,
      "u"
    ],
    [
      0.090044,
      "s"
    ],
    [
      0.112389,
      "\r\n"
    ],
    [
      0.145173,
      "running\r\n"
    ],
    [
      0.000578,
      "bash-3.2$ "
    ],
    [
      41.693312,
      "e"
    ],
    [
      0.134747,
      "x"
    ],
    [
      0.101017,
      "i"
    ],
    [
      0.090063,
      "t"
    ],
    [
      0.078729,
      "\r\n"
    ],
    [
      0.000087,
      "exit\r\n"
    ]
  ]
}