[[0.096854,{"lines":{"0":[["                                                                                         ",{}]],"1":[["                                                                                         ",{}]],"2":[["                                                                                         ",{}]],"3":[["                                                                                         ",{}]],"4":[["                                                                                         ",{}]],"5":[["                                                                                         ",{}]],"6":[["                                                                                         ",{}]],"7":[["                                                                                         ",{}]],"8":[["                                                                                         ",{}]],"9":[["                                                                                         ",{}]],"10":[["                                                                                         ",{}]],"11":[["                                                                                         ",{}]],"12":[["                                                                                         ",{}]],"13":[["                                                                                         ",{}]],"14":[["                                                                                         ",{}]],"15":[["                                                                                         ",{}]],"16":[["                                                                                         ",{}]],"17":[["                                                                                         ",{}]],"18":[["                                                                                         ",{}]],"19":[["                                                                                         ",{}]],"20":[["                                                                                         ",{}]],"21":[["                                                                                         ",{}]],"22":[["                                                                                         ",{}]],"23":[["                                                                                         ",{}]],"24":[["                                                                                         ",{}]],"25":[["                                                                                         ",{}]],"26":[["                                                                                         ",{}]],"27":[["                                                                                         ",{}]],"28":[["                                                                                         ",{}]]},"cursor":{"x":0,"y":0,"visible":true}}],[7.1e-05,{"lines":{"0":[["[tpa@zapt ~]$                                                                            ",{}]]},"cursor":{"x":14}}],[0.815804,{"lines":{"0":[["[tpa@zapt ~]$ s                                                                          ",{}]]},"cursor":{"x":15}}],[0.175819,{"lines":{"0":[["[tpa@zapt ~]$ ss                                                                         ",{}]]},"cursor":{"x":16}}],[0.096336,{"lines":{"0":[["[tpa@zapt ~]$ ssh                                                                        ",{}]]},"cursor":{"x":17}}],[0.09683,{"cursor":{"x":18}}],[0.112054,{"lines":{"0":[["[tpa@zapt ~]$ ssh t                                                                      ",{}]]},"cursor":{"x":19}}],[0.063336,{"lines":{"0":[["[tpa@zapt ~]$ ssh te                                                                     ",{}]]},"cursor":{"x":20}}],[0.080155,{"lines":{"0":[["[tpa@zapt ~]$ ssh tes                                                                    ",{}]]},"cursor":{"x":21}}],[0.08107300000000001,{"lines":{"0":[["[tpa@zapt ~]$ ssh test                                                                   ",{}]]},"cursor":{"x":22}}],[0.111239,{"lines":{"0":[["[tpa@zapt ~]$ ssh testu                                                                  ",{}]]},"cursor":{"x":23}}],[0.111852,{"lines":{"0":[["[tpa@zapt ~]$ ssh testus                                                                 ",{}]]},"cursor":{"x":24}}],[0.048054,{"lines":{"0":[["[tpa@zapt ~]$ ssh testuse                                                                ",{}]]},"cursor":{"x":25}}],[0.08064499999999999,{"lines":{"0":[["[tpa@zapt ~]$ ssh testuser                                                               ",{}]]},"cursor":{"x":26}}],[0.303931,{"lines":{"0":[["[tpa@zapt ~]$ ssh testuser@                                                              ",{}]]},"cursor":{"x":27}}],[0.304055,{"lines":{"0":[["[tpa@zapt ~]$ ssh testuser@l                                                             ",{}]]},"cursor":{"x":28}}],[0.159981,{"lines":{"0":[["[tpa@zapt ~]$ ssh testuser@lo                                                            ",{}]]},"cursor":{"x":29}}],[0.06351800000000001,{"lines":{"0":[["[tpa@zapt ~]$ ssh testuser@lon                                                           ",{}]]},"cursor":{"x":30}}],[0.095806,{"lines":{"0":[["[tpa@zapt ~]$ ssh testuser@long                                                          ",{}]]},"cursor":{"x":31}}],[0.128051,{"lines":{"0":[["[tpa@zapt ~]$ ssh testuser@long.                                                         ",{}]]},"cursor":{"x":32}}],[0.127952,{"lines":{"0":[["[tpa@zapt ~]$ ssh testuser@long.t                                                        ",{}]]},"cursor":{"x":33}}],[0.080113,{"lines":{"0":[["[tpa@zapt ~]$ ssh testuser@long.te                                                       ",{}]]},"cursor":{"x":34}}],[0.175995,{"lines":{"0":[["[tpa@zapt ~]$ ssh testuser@long.ted                                                      ",{}]]},"cursor":{"x":35}}],[0.080058,{"lines":{"0":[["[tpa@zapt ~]$ ssh testuser@long.tedi                                                     ",{}]]},"cursor":{"x":36}}],[0.096439,{"lines":{"0":[["[tpa@zapt ~]$ ssh testuser@long.tedio                                                    ",{}]]},"cursor":{"x":37}}],[0.09546399999999999,{"lines":{"0":[["[tpa@zapt ~]$ ssh testuser@long.tediou                                                   ",{}]]},"cursor":{"x":38}}],[0.159957,{"lines":{"0":[["[tpa@zapt ~]$ ssh testuser@long.tedious                                                  ",{}]]},"cursor":{"x":39}}],[0.112007,{"lines":{"0":[["[tpa@zapt ~]$ ssh testuser@long.tedious.                                                 ",{}]]},"cursor":{"x":40}}],[0.192035,{"lines":{"0":[["[tpa@zapt ~]$ ssh testuser@long.tedious.d                                                ",{}]]},"cursor":{"x":41}}],[0.080777,{"lines":{"0":[["[tpa@zapt ~]$ ssh testuser@long.tedious.do                                               ",{}]]},"cursor":{"x":42}}],[0.079264,{"lines":{"0":[["[tpa@zapt ~]$ ssh testuser@long.tedious.dom                                              ",{}]]},"cursor":{"x":43}}],[0.127936,{"lines":{"0":[["[tpa@zapt ~]$ ssh testuser@long.tedious.doma                                             ",{}]]},"cursor":{"x":44}}],[0.06396399999999999,{"lines":{"0":[["[tpa@zapt ~]$ ssh testuser@long.tedious.domai                                            ",{}]]},"cursor":{"x":45}}],[0.048727,{"lines":{"0":[["[tpa@zapt ~]$ ssh testuser@long.tedious.domain                                           ",{}]]},"cursor":{"x":46}}],[0.159304,{"lines":{"0":[["[tpa@zapt ~]$ ssh testuser@long.tedious.domain.                                          ",{}]]},"cursor":{"x":47}}],[0.176083,{"lines":{"0":[["[tpa@zapt ~]$ ssh testuser@long.tedious.domain.n                                         ",{}]]},"cursor":{"x":48}}],[0.03175,{"lines":{"0":[["[tpa@zapt ~]$ ssh testuser@long.tedious.domain.na                                        ",{}]]},"cursor":{"x":49}}],[0.160817,{"lines":{"0":[["[tpa@zapt ~]$ ssh testuser@long.tedious.domain.nam                                       ",{}]]},"cursor":{"x":50}}],[0.143528,{"lines":{"0":[["[tpa@zapt ~]$ ssh testuser@long.tedious.domain.name                                      ",{}]]},"cursor":{"x":51}}],[0.319901,{"cursor":{"x":0,"y":1}}],[0.16179,{"lines":{"1":[["testuser@long.tedious.domain.name's password:                                            ",{}]]},"cursor":{"x":46}}],[3.182742,{"cursor":{"x":0,"y":2}}],[2.247413,{"lines":{"2":[["[testuser@dogwood00 ~]$                                                                  ",{}]]},"cursor":{"x":24}}],[3.517471,{"lines":{"2":[["[testuser@dogwood00 ~]$ logout                                                           ",{}]],"3":[["Connection to long.tedious.domain.name closed.                                           ",{}]]},"cursor":{"x":0,"y":4}}],[0.000559,{"lines":{"4":[["[tpa@zapt ~]$                                                                            ",{}]]},"cursor":{"x":14}}],[1.098568,{"lines":{"4":[["[tpa@zapt ~]$ s                                                                          ",{}]]},"cursor":{"x":15}}],[0.144002,{"lines":{"4":[["[tpa@zapt ~]$ ss                                                                         ",{}]]},"cursor":{"x":16}}],[0.09622600000000001,{"lines":{"4":[["[tpa@zapt ~]$ ssh                                                                        ",{}]]},"cursor":{"x":17}}],[0.191285,{"lines":{"4":[["[tpa@zapt ~]$ ssh-                                                                       ",{}]]},"cursor":{"x":18}}],[0.255931,{"lines":{"4":[["[tpa@zapt ~]$ ssh-k                                                                      ",{}]]},"cursor":{"x":19}}],[0.176661,{"lines":{"4":[["[tpa@zapt ~]$ ssh-ke                                                                     ",{}]]},"cursor":{"x":20}}],[0.080196,{"lines":{"4":[["[tpa@zapt ~]$ ssh-key                                                                    ",{}]]},"cursor":{"x":21}}],[0.143129,{"lines":{"4":[["[tpa@zapt ~]$ ssh-keyg                                                                   ",{}]]},"cursor":{"x":22}}],[0.159954,{"lines":{"4":[["[tpa@zapt ~]$ ssh-keyge                                                                  ",{}]]},"cursor":{"x":23}}],[0.160122,{"lines":{"4":[["[tpa@zapt ~]$ ssh-keygen                                                                 ",{}]]},"cursor":{"x":24}}],[0.6405920000000001,{"cursor":{"x":0,"y":5}}],[0.005676,{"lines":{"5":[["Generating public/private rsa key pair.                                                  ",{}]]},"cursor":{"y":6}}],[0.227977,{"lines":{"6":[["Enter file in which to save the key (/home/tpa/.ssh/id_rsa):                             ",{}]]},"cursor":{"x":61}}],[1.014257,{"cursor":{"x":0,"y":7}}],[0.000127,{"lines":{"7":[["Enter passphrase (empty for no passphrase):                                              ",{}]]},"cursor":{"x":44}}],[0.911956,{"cursor":{"x":0,"y":8}}],[9.3e-05,{"lines":{"8":[["Enter same passphrase again:                                                             ",{}]]},"cursor":{"x":29}}],[0.815921,{"cursor":{"x":0,"y":9}}],[0.002118,{"lines":{"9":[["Your identification has been saved in /home/tpa/.ssh/id_rsa.                             ",{}]],"10":[["Your public key has been saved in /home/tpa/.ssh/id_rsa.pub.                             ",{}]],"11":[["The key fingerprint is:                                                                  ",{}]],"12":[["82:9f:6f:cc:92:9d:e3:78:d5:8f:34:c4:48:7b:13:07 tpa@zapt                                 ",{}]],"13":[["The key's randomart image is:                                                            ",{}]],"14":[["+--[ RSA 2048]----+                                                                      ",{}]],"15":[["|            E.   |                                                                      ",{}]],"16":[["|          . . .  |                                                                      ",{}]],"17":[["|         . + o   |                                                                      ",{}]],"18":[["|     .    o =    |                                                                      ",{}]],"19":[["|    . . S  + .   |                                                                      ",{}]],"20":[["|     . o  . +    |                                                                      ",{}]],"21":[["|      o= o . +   |                                                                      ",{}]],"22":[["|      ooO   . .  |                                                                      ",{}]],"23":[["|      .=o.       |                                                                      ",{}]],"24":[["+-----------------+                                                                      ",{}]],"25":[["[tpa@zapt ~]$                                                                            ",{}]]},"cursor":{"x":14,"y":25}}],[1.981969,{"lines":{"25":[["[tpa@zapt ~]$ /                                                                          ",{}]]},"cursor":{"x":15}}],[0.23942,{"lines":{"25":[["[tpa@zapt ~]$ /s                                                                         ",{}]]},"cursor":{"x":16}}],[0.127968,{"lines":{"25":[["[tpa@zapt ~]$ /ss                                                                        ",{}]]},"cursor":{"x":17}}],[0.080772,{"lines":{"25":[["[tpa@zapt ~]$ /ssh                                                                       ",{}]]},"cursor":{"x":18}}],[0.207305,{"lines":{"25":[["[tpa@zapt ~]$ ssh-keygen                                                                 ",{}]]},"cursor":{"x":14}}],[0.75259,{"lines":{"25":[["[tpa@zapt ~]$ ssh testuser@long.tedious.domain.name                                      ",{}]]}}],[5.615933,{"cursor":{"x":16}}],[0.4478,{"cursor":{"x":17}}],[0.192423,{"lines":{"25":[["[tpa@zapt ~]$ ssh- testuser@long.tedious.domain.name                                     ",{}]]},"cursor":{"x":18}}],[0.159552,{"lines":{"25":[["[tpa@zapt ~]$ ssh-c testuser@long.tedious.domain.name                                    ",{}]]},"cursor":{"x":19}}],[0.08053100000000001,{"lines":{"25":[["[tpa@zapt ~]$ ssh-co testuser@long.tedious.domain.name                                   ",{}]]},"cursor":{"x":20}}],[0.047447,{"lines":{"25":[["[tpa@zapt ~]$ ssh-cop testuser@long.tedious.domain.name                                  ",{}]]},"cursor":{"x":21}}],[0.159906,{"lines":{"25":[["[tpa@zapt ~]$ ssh-copy testuser@long.tedious.domain.name                                 ",{}]]},"cursor":{"x":22}}],[0.192118,{"lines":{"25":[["[tpa@zapt ~]$ ssh-copy- testuser@long.tedious.domain.name                                ",{}]]},"cursor":{"x":23}}],[0.192016,{"lines":{"25":[["[tpa@zapt ~]$ ssh-copy-i testuser@long.tedious.domain.name                               ",{}]]},"cursor":{"x":24}}],[0.08058999999999999,{"lines":{"25":[["[tpa@zapt ~]$ ssh-copy-id testuser@long.tedious.domain.name                              ",{}]]},"cursor":{"x":25}}],[1.359569,{"cursor":{"x":0,"y":26}}],[0.149929,{"lines":{"26":[["/bin/ssh-copy-id: INFO: attempting to log in with the new key(s), to filter out any that ",{}]],"27":[["are already installed                                                                    ",{}]]},"cursor":{"y":28}}],[0.196853,{"lines":{"0":[["[testuser@dogwood00 ~]$ logout                                                           ",{}]],"1":[["Connection to long.tedious.domain.name closed.                                           ",{}]],"2":[["[tpa@zapt ~]$ ssh-keygen                                                                 ",{}]],"3":[["Generating public/private rsa key pair.                                                  ",{}]],"4":[["Enter file in which to save the key (/home/tpa/.ssh/id_rsa):                             ",{}]],"5":[["Enter passphrase (empty for no passphrase):                                              ",{}]],"6":[["Enter same passphrase again:                                                             ",{}]],"7":[["Your identification has been saved in /home/tpa/.ssh/id_rsa.                             ",{}]],"8":[["Your public key has been saved in /home/tpa/.ssh/id_rsa.pub.                             ",{}]],"9":[["The key fingerprint is:                                                                  ",{}]],"10":[["82:9f:6f:cc:92:9d:e3:78:d5:8f:34:c4:48:7b:13:07 tpa@zapt                                 ",{}]],"11":[["The key's randomart image is:                                                            ",{}]],"12":[["+--[ RSA 2048]----+                                                                      ",{}]],"13":[["|            E.   |                                                                      ",{}]],"14":[["|          . . .  |                                                                      ",{}]],"15":[["|         . + o   |                                                                      ",{}]],"16":[["|     .    o =    |                                                                      ",{}]],"17":[["|    . . S  + .   |                                                                      ",{}]],"18":[["|     . o  . +    |                                                                      ",{}]],"19":[["|      o= o . +   |                                                                      ",{}]],"20":[["|      ooO   . .  |                                                                      ",{}]],"21":[["|      .=o.       |                                                                      ",{}]],"22":[["+-----------------+                                                                      ",{}]],"23":[["[tpa@zapt ~]$ ssh-copy-id testuser@long.tedious.domain.name                              ",{}]],"24":[["/bin/ssh-copy-id: INFO: attempting to log in with the new key(s), to filter out any that ",{}]],"25":[["are already installed                                                                    ",{}]],"26":[["/bin/ssh-copy-id: INFO: 1 key(s) remain to be installed -- if you are prompted now it is ",{}]],"27":[["to install the new keys                                                                  ",{}]]}}],[0.143302,{"lines":{"28":[["testuser@long.tedious.domain.name's password:                                            ",{}]]},"cursor":{"x":46}}],[4.390002,{"lines":{"0":[["Connection to long.tedious.domain.name closed.                                           ",{}]],"1":[["[tpa@zapt ~]$ ssh-keygen                                                                 ",{}]],"2":[["Generating public/private rsa key pair.                                                  ",{}]],"3":[["Enter file in which to save the key (/home/tpa/.ssh/id_rsa):                             ",{}]],"4":[["Enter passphrase (empty for no passphrase):                                              ",{}]],"5":[["Enter same passphrase again:                                                             ",{}]],"6":[["Your identification has been saved in /home/tpa/.ssh/id_rsa.                             ",{}]],"7":[["Your public key has been saved in /home/tpa/.ssh/id_rsa.pub.                             ",{}]],"8":[["The key fingerprint is:                                                                  ",{}]],"9":[["82:9f:6f:cc:92:9d:e3:78:d5:8f:34:c4:48:7b:13:07 tpa@zapt                                 ",{}]],"10":[["The key's randomart image is:                                                            ",{}]],"11":[["+--[ RSA 2048]----+                                                                      ",{}]],"12":[["|            E.   |                                                                      ",{}]],"13":[["|          . . .  |                                                                      ",{}]],"14":[["|         . + o   |                                                                      ",{}]],"15":[["|     .    o =    |                                                                      ",{}]],"16":[["|    . . S  + .   |                                                                      ",{}]],"17":[["|     . o  . +    |                                                                      ",{}]],"18":[["|      o= o . +   |                                                                      ",{}]],"19":[["|      ooO   . .  |                                                                      ",{}]],"20":[["|      .=o.       |                                                                      ",{}]],"21":[["+-----------------+                                                                      ",{}]],"22":[["[tpa@zapt ~]$ ssh-copy-id testuser@long.tedious.domain.name                              ",{}]],"23":[["/bin/ssh-copy-id: INFO: attempting to log in with the new key(s), to filter out any that ",{}]],"24":[["are already installed                                                                    ",{}]],"25":[["/bin/ssh-copy-id: INFO: 1 key(s) remain to be installed -- if you are prompted now it is ",{}]],"26":[["to install the new keys                                                                  ",{}]],"27":[["testuser@long.tedious.domain.name's password:                                            ",{}]],"28":[["                                                                                         ",{}]]},"cursor":{"x":0}}],[2.194505,{"lines":{"0":[["Your identification has been saved in /home/tpa/.ssh/id_rsa.                             ",{}]],"1":[["Your public key has been saved in /home/tpa/.ssh/id_rsa.pub.                             ",{}]],"2":[["The key fingerprint is:                                                                  ",{}]],"3":[["82:9f:6f:cc:92:9d:e3:78:d5:8f:34:c4:48:7b:13:07 tpa@zapt                                 ",{}]],"4":[["The key's randomart image is:                                                            ",{}]],"5":[["+--[ RSA 2048]----+                                                                      ",{}]],"6":[["|            E.   |                                                                      ",{}]],"7":[["|          . . .  |                                                                      ",{}]],"8":[["|         . + o   |                                                                      ",{}]],"9":[["|     .    o =    |                                                                      ",{}]],"10":[["|    . . S  + .   |                                                                      ",{}]],"11":[["|     . o  . +    |                                                                      ",{}]],"12":[["|      o= o . +   |                                                                      ",{}]],"13":[["|      ooO   . .  |                                                                      ",{}]],"14":[["|      .=o.       |                                                                      ",{}]],"15":[["+-----------------+                                                                      ",{}]],"16":[["[tpa@zapt ~]$ ssh-copy-id testuser@long.tedious.domain.name                              ",{}]],"17":[["/bin/ssh-copy-id: INFO: attempting to log in with the new key(s), to filter out any that ",{}]],"18":[["are already installed                                                                    ",{}]],"19":[["/bin/ssh-copy-id: INFO: 1 key(s) remain to be installed -- if you are prompted now it is ",{}]],"20":[["to install the new keys                                                                  ",{}]],"21":[["testuser@long.tedious.domain.name's password:                                            ",{}]],"22":[["                                                                                         ",{}]],"23":[["Number of key(s) added: 1                                                                ",{}]],"24":[["                                                                                         ",{}]],"25":[["Now try logging into the machine, with:   \"ssh 'testuser@long.tedious.domain.name'\"      ",{}]],"26":[["and check to make sure that only the key(s) you wanted were added.                       ",{}]],"27":[["                                                                                         ",{}]]}}],[0.000769,{"lines":{"28":[["[tpa@zapt ~]$                                                                            ",{}]]},"cursor":{"x":14}}],[3.452343,{"lines":{"28":[["[tpa@zapt ~]$ /                                                                          ",{}]]},"cursor":{"x":15}}],[0.143858,{"lines":{"28":[["[tpa@zapt ~]$ /s                                                                         ",{}]]},"cursor":{"x":16}}],[0.144043,{"lines":{"28":[["[tpa@zapt ~]$ /ss                                                                        ",{}]]},"cursor":{"x":17}}],[0.064058,{"lines":{"28":[["[tpa@zapt ~]$ /ssh                                                                       ",{}]]},"cursor":{"x":18}}],[0.175978,{"lines":{"28":[["[tpa@zapt ~]$ ssh-copy-id testuser@long.tedious.domain.name                              ",{}]]},"cursor":{"x":14}}],[0.512554,{"lines":{"28":[["[tpa@zapt ~]$ ssh-keygen                                                                 ",{}]]}}],[0.5119320000000001,{"lines":{"28":[["[tpa@zapt ~]$ ssh testuser@long.tedious.domain.name                                      ",{}]]}}],[1.215955,{"lines":{"0":[["Your public key has been saved in /home/tpa/.ssh/id_rsa.pub.                             ",{}]],"1":[["The key fingerprint is:                                                                  ",{}]],"2":[["82:9f:6f:cc:92:9d:e3:78:d5:8f:34:c4:48:7b:13:07 tpa@zapt                                 ",{}]],"3":[["The key's randomart image is:                                                            ",{}]],"4":[["+--[ RSA 2048]----+                                                                      ",{}]],"5":[["|            E.   |                                                                      ",{}]],"6":[["|          . . .  |                                                                      ",{}]],"7":[["|         . + o   |                                                                      ",{}]],"8":[["|     .    o =    |                                                                      ",{}]],"9":[["|    . . S  + .   |                                                                      ",{}]],"10":[["|     . o  . +    |                                                                      ",{}]],"11":[["|      o= o . +   |                                                                      ",{}]],"12":[["|      ooO   . .  |                                                                      ",{}]],"13":[["|      .=o.       |                                                                      ",{}]],"14":[["+-----------------+                                                                      ",{}]],"15":[["[tpa@zapt ~]$ ssh-copy-id testuser@long.tedious.domain.name                              ",{}]],"16":[["/bin/ssh-copy-id: INFO: attempting to log in with the new key(s), to filter out any that ",{}]],"17":[["are already installed                                                                    ",{}]],"18":[["/bin/ssh-copy-id: INFO: 1 key(s) remain to be installed -- if you are prompted now it is ",{}]],"19":[["to install the new keys                                                                  ",{}]],"20":[["testuser@long.tedious.domain.name's password:                                            ",{}]],"21":[["                                                                                         ",{}]],"22":[["Number of key(s) added: 1                                                                ",{}]],"23":[["                                                                                         ",{}]],"24":[["Now try logging into the machine, with:   \"ssh 'testuser@long.tedious.domain.name'\"      ",{}]],"25":[["and check to make sure that only the key(s) you wanted were added.                       ",{}]],"26":[["                                                                                         ",{}]],"27":[["[tpa@zapt ~]$ ssh testuser@long.tedious.domain.name                                      ",{}]],"28":[["                                                                                         ",{}]]},"cursor":{"x":0}}],[2.524741,{}],[0.001773,{"lines":{"28":[["[testuser@dogwood00 ~]$                                                                  ",{}]]},"cursor":{"x":24}}],[9.66234,{"lines":{"0":[["The key fingerprint is:                                                                  ",{}]],"1":[["82:9f:6f:cc:92:9d:e3:78:d5:8f:34:c4:48:7b:13:07 tpa@zapt                                 ",{}]],"2":[["The key's randomart image is:                                                            ",{}]],"3":[["+--[ RSA 2048]----+                                                                      ",{}]],"4":[["|            E.   |                                                                      ",{}]],"5":[["|          . . .  |                                                                      ",{}]],"6":[["|         . + o   |                                                                      ",{}]],"7":[["|     .    o =    |                                                                      ",{}]],"8":[["|    . . S  + .   |                                                                      ",{}]],"9":[["|     . o  . +    |                                                                      ",{}]],"10":[["|      o= o . +   |                                                                      ",{}]],"11":[["|      ooO   . .  |                                                                      ",{}]],"12":[["|      .=o.       |                                                                      ",{}]],"13":[["+-----------------+                                                                      ",{}]],"14":[["[tpa@zapt ~]$ ssh-copy-id testuser@long.tedious.domain.name                              ",{}]],"15":[["/bin/ssh-copy-id: INFO: attempting to log in with the new key(s), to filter out any that ",{}]],"16":[["are already installed                                                                    ",{}]],"17":[["/bin/ssh-copy-id: INFO: 1 key(s) remain to be installed -- if you are prompted now it is ",{}]],"18":[["to install the new keys                                                                  ",{}]],"19":[["testuser@long.tedious.domain.name's password:                                            ",{}]],"20":[["                                                                                         ",{}]],"21":[["Number of key(s) added: 1                                                                ",{}]],"22":[["                                                                                         ",{}]],"23":[["Now try logging into the machine, with:   \"ssh 'testuser@long.tedious.domain.name'\"      ",{}]],"24":[["and check to make sure that only the key(s) you wanted were added.                       ",{}]],"25":[["                                                                                         ",{}]],"26":[["[tpa@zapt ~]$ ssh testuser@long.tedious.domain.name                                      ",{}]],"27":[["[testuser@dogwood00 ~]$ logout                                                           ",{}]],"28":[["                                                                                         ",{}]]},"cursor":{"x":0}}],[0.001813,{"lines":{"0":[["82:9f:6f:cc:92:9d:e3:78:d5:8f:34:c4:48:7b:13:07 tpa@zapt                                 ",{}]],"1":[["The key's randomart image is:                                                            ",{}]],"2":[["+--[ RSA 2048]----+                                                                      ",{}]],"3":[["|            E.   |                                                                      ",{}]],"4":[["|          . . .  |                                                                      ",{}]],"5":[["|         . + o   |                                                                      ",{}]],"6":[["|     .    o =    |                                                                      ",{}]],"7":[["|    . . S  + .   |                                                                      ",{}]],"8":[["|     . o  . +    |                                                                      ",{}]],"9":[["|      o= o . +   |                                                                      ",{}]],"10":[["|      ooO   . .  |                                                                      ",{}]],"11":[["|      .=o.       |                                                                      ",{}]],"12":[["+-----------------+                                                                      ",{}]],"13":[["[tpa@zapt ~]$ ssh-copy-id testuser@long.tedious.domain.name                              ",{}]],"14":[["/bin/ssh-copy-id: INFO: attempting to log in with the new key(s), to filter out any that ",{}]],"15":[["are already installed                                                                    ",{}]],"16":[["/bin/ssh-copy-id: INFO: 1 key(s) remain to be installed -- if you are prompted now it is ",{}]],"17":[["to install the new keys                                                                  ",{}]],"18":[["testuser@long.tedious.domain.name's password:                                            ",{}]],"19":[["                                                                                         ",{}]],"20":[["Number of key(s) added: 1                                                                ",{}]],"21":[["                                                                                         ",{}]],"22":[["Now try logging into the machine, with:   \"ssh 'testuser@long.tedious.domain.name'\"      ",{}]],"23":[["and check to make sure that only the key(s) you wanted were added.                       ",{}]],"24":[["                                                                                         ",{}]],"25":[["[tpa@zapt ~]$ ssh testuser@long.tedious.domain.name                                      ",{}]],"26":[["[testuser@dogwood00 ~]$ logout                                                           ",{}]],"27":[["Connection to long.tedious.domain.name closed.                                           ",{}]],"28":[["[tpa@zapt ~]$                                                                            ",{}]]},"cursor":{"x":14}}],[2.177563,{"lines":{"28":[["[tpa@zapt ~]$ v                                                                          ",{}]]},"cursor":{"x":15}}],[0.046752,{"lines":{"28":[["[tpa@zapt ~]$ vi                                                                         ",{}]]},"cursor":{"x":16}}],[0.065027,{"lines":{"28":[["[tpa@zapt ~]$ vim                                                                        ",{}]]},"cursor":{"x":17}}],[0.07940899999999999,{"cursor":{"x":18}}],[0.112146,{"lines":{"28":[["[tpa@zapt ~]$ vim .                                                                      ",{}]]},"cursor":{"x":19}}],[0.127983,{"lines":{"28":[["[tpa@zapt ~]$ vim .c                                                                     ",{}]]},"cursor":{"x":20}}],[0.560564,{"lines":{"28":[["[tpa@zapt ~]$ vim .                                                                      ",{}]]},"cursor":{"x":19}}],[0.063966,{"lines":{"28":[["[tpa@zapt ~]$ vim .s                                                                     ",{}]]},"cursor":{"x":20}}],[0.159657,{"lines":{"28":[["[tpa@zapt ~]$ vim .ss                                                                    ",{}]]},"cursor":{"x":21}}],[0.124081,{"lines":{"28":[["[tpa@zapt ~]$ vim .ssh/                                                                  ",{}]]},"cursor":{"x":23}}],[0.147705,{"lines":{"28":[["[tpa@zapt ~]$ vim .ssh/c                                                                 ",{}]]},"cursor":{"x":24}}],[0.06458899999999999,{"lines":{"28":[["[tpa@zapt ~]$ vim .ssh/co                                                                ",{}]]},"cursor":{"x":25}}],[0.09189899999999999,{}],[0.900123,{"lines":{"28":[["[tpa@zapt ~]$ vim .ssh/con                                                               ",{}]]},"cursor":{"x":26}}],[0.096692,{"lines":{"28":[["[tpa@zapt ~]$ vim .ssh/conf                                                              ",{}]]},"cursor":{"x":27}}],[0.094684,{"lines":{"28":[["[tpa@zapt ~]$ vim .ssh/confi                                                             ",{}]]},"cursor":{"x":28}}],[0.096889,{"lines":{"28":[["[tpa@zapt ~]$ vim .ssh/config                                                            ",{}]]},"cursor":{"x":29}}],[0.187401,{}],[0.388354,{"lines":{"0":[["The key's randomart image is:                                                            ",{}]],"1":[["+--[ RSA 2048]----+                                                                      ",{}]],"2":[["|            E.   |                                                                      ",{}]],"3":[["|          . . .  |                                                                      ",{}]],"4":[["|         . + o   |                                                                      ",{}]],"5":[["|     .    o =    |                                                                      ",{}]],"6":[["|    . . S  + .   |                                                                      ",{}]],"7":[["|     . o  . +    |                                                                      ",{}]],"8":[["|      o= o . +   |                                                                      ",{}]],"9":[["|      ooO   . .  |                                                                      ",{}]],"10":[["|      .=o.       |                                                                      ",{}]],"11":[["+-----------------+                                                                      ",{}]],"12":[["[tpa@zapt ~]$ ssh-copy-id testuser@long.tedious.domain.name                              ",{}]],"13":[["/bin/ssh-copy-id: INFO: attempting to log in with the new key(s), to filter out any that ",{}]],"14":[["are already installed                                                                    ",{}]],"15":[["/bin/ssh-copy-id: INFO: 1 key(s) remain to be installed -- if you are prompted now it is ",{}]],"16":[["to install the new keys                                                                  ",{}]],"17":[["testuser@long.tedious.domain.name's password:                                            ",{}]],"18":[["                                                                                         ",{}]],"19":[["Number of key(s) added: 1                                                                ",{}]],"20":[["                                                                                         ",{}]],"21":[["Now try logging into the machine, with:   \"ssh 'testuser@long.tedious.domain.name'\"      ",{}]],"22":[["and check to make sure that only the key(s) you wanted were added.                       ",{}]],"23":[["                                                                                         ",{}]],"24":[["[tpa@zapt ~]$ ssh testuser@long.tedious.domain.name                                      ",{}]],"25":[["[testuser@dogwood00 ~]$ logout                                                           ",{}]],"26":[["Connection to long.tedious.domain.name closed.                                           ",{}]],"27":[["[tpa@zapt ~]$ vim .ssh/config                                                            ",{}]],"28":[["                                                                                         ",{}]]},"cursor":{"x":0}}],[0.065357,{"lines":{"0":[["                                                                                         ",{}]],"1":[["                                                                                         ",{}]],"2":[["                                                                                         ",{}]],"3":[["                                                                                         ",{}]],"4":[["                                                                                         ",{}]],"5":[["                                                                                         ",{}]],"6":[["                                                                                         ",{}]],"7":[["                                                                                         ",{}]],"8":[["                                                                                         ",{}]],"9":[["                                                                                         ",{}]],"10":[["                                                                                         ",{}]],"11":[["                                                                                         ",{}]],"12":[["                                                                                         ",{}]],"13":[["                                                                                         ",{}]],"14":[["                                                                                         ",{}]],"15":[["                                                                                         ",{}]],"16":[["                                                                                         ",{}]],"17":[["                                                                                         ",{}]],"19":[["                                                                                         ",{}]],"21":[["                                                                                         ",{}]],"22":[["                                                                                         ",{}]],"24":[["                                                                                         ",{}]],"25":[["                                                                                         ",{}]],"26":[["                                                                                         ",{}]],"27":[["                                                                                         ",{}]]},"cursor":{"y":0}}],[0.011855,{"lines":{"1":[["~                                                                                        ",{"fg":12}]],"2":[["~                                                                                        ",{"fg":12}]],"3":[["~                                                                                        ",{"fg":12}]],"4":[["~                                                                                        ",{"fg":12}]],"5":[["~                                                                                        ",{"fg":12}]],"6":[["~                                                                                        ",{"fg":12}]],"7":[["~                                                                                        ",{"fg":12}]],"8":[["~                                                                                        ",{"fg":12}]],"9":[["~                                                                                        ",{"fg":12}]],"10":[["~                                                                                        ",{"fg":12}]],"11":[["~                                                                                        ",{"fg":12}]],"12":[["~                                                                                        ",{"fg":12}]],"13":[["~                                                                                        ",{"fg":12}]],"14":[["~                                                                                        ",{"fg":12}]],"15":[["~                                                                                        ",{"fg":12}]],"16":[["~                                                                                        ",{"fg":12}]],"17":[["~                                                                                        ",{"fg":12}]],"18":[["~                                                                                        ",{"fg":12}]],"19":[["~                                                                                        ",{"fg":12}]],"20":[["~                                                                                        ",{"fg":12}]],"21":[["~                                                                                        ",{"fg":12}]],"22":[["~                                                                                        ",{"fg":12}]],"23":[["~                                                                                        ",{"fg":12}]],"24":[["~                                                                                        ",{"fg":12}]],"25":[["~                                                                                        ",{"fg":12}]],"26":[["~                                                                                        ",{"fg":12}]],"27":[["~                                                                                        ",{"fg":12}]],"28":[["\".ssh/config\" [New File]                                               0,0-1         All ",{}]]}}],[0.673687,{"lines":{"28":[[":                                                                                        ",{}]]},"cursor":{"x":1,"y":28}}],[0.160798,{"lines":{"28":[[":s                                                                                       ",{}]]},"cursor":{"x":2}}],[5.5e-05,{}],[0.078962,{"lines":{"28":[[":se                                                                                      ",{}]]},"cursor":{"x":3}}],[0.048105,{"lines":{"28":[[":set                                                                                     ",{}]]},"cursor":{"x":4}}],[0.047949,{"cursor":{"x":5}}],[0.080444,{"lines":{"28":[[":set p                                                                                   ",{}]]},"cursor":{"x":6}}],[0.09689200000000001,{"lines":{"28":[[":set pa                                                                                  ",{}]]},"cursor":{"x":7}}],[0.04717,{"lines":{"28":[[":set pas                                                                                 ",{}]]},"cursor":{"x":8}}],[0.048004,{"lines":{"28":[[":set past                                                                                ",{}]]},"cursor":{"x":9}}],[0.080152,{"lines":{"28":[[":set paste                                                                               ",{}]]},"cursor":{"x":10}}],[0.128047,{"cursor":{"x":0,"y":0}}],[0.192138,{"lines":{"28":[["-- INSERT (paste) --",{"bold":true}],["                                                                     ",{}]]}}],[0.929935,{"lines":{"0":[["Host",{"fg":2}],[" ",{}],["dogwood00",{"fg":1}],["                                                                           ",{}]],"1":[["    ",{}],["Hostname",{"fg":130}],[" ",{}],["long.tedious.domain.name",{"fg":1}],["                                                    ",{}]],"2":[["    ",{}],["User",{"fg":130}],[" testuser                                                                        ",{}]],"3":[["                                                                                         ",{}]],"4":[["Host",{"fg":2}],[" ",{}],["dogwood01",{"fg":1}],["                                                                           ",{}]],"5":[["    ",{}],["Hostname",{"fg":130}],[" dogwood",{}],["01",{"fg":1}],["                                                                   ",{}]],"6":[["    ",{}],["User",{"fg":130}],[" testuser                                                                        ",{}]],"7":[["    ",{}],["ProxyCommand",{"fg":130}],[" ssh dogwood",{}],["00",{"fg":1}],[" -W ",{}],["%h",{"fg":6}],[":",{}],["%p",{"fg":6}],["                                                  ",{}]]},"cursor":{"x":39,"y":7}}],[1.303582,{"lines":{"28":[["                                                                                         ",{}]]},"cursor":{"x":38}}],[1.001416,{}],[0.317611,{"lines":{"28":[[":                                                                                        ",{}]]},"cursor":{"x":1,"y":28}}],[0.175232,{"lines":{"28":[[":x                                                                                       ",{}]]},"cursor":{"x":2}}],[16.017472,{"lines":{"28":[["\".ssh/config\"                                                                            ",{}]]},"cursor":{"x":13,"visible":false}}],[0.017438,{"lines":{"0":[["The key's randomart image is:                                                            ",{}]],"1":[["+--[ RSA 2048]----+                                                                      ",{}]],"2":[["|            E.   |                                                                      ",{}]],"3":[["|          . . .  |                                                                      ",{}]],"4":[["|         . + o   |                                                                      ",{}]],"5":[["|     .    o =    |                                                                      ",{}]],"6":[["|    . . S  + .   |                                                                      ",{}]],"7":[["|     . o  . +    |                                                                      ",{}]],"8":[["|      o= o . +   |                                                                      ",{}]],"9":[["|      ooO   . .  |                                                                      ",{}]],"10":[["|      .=o.       |                                                                      ",{}]],"11":[["+-----------------+                                                                      ",{}]],"12":[["[tpa@zapt ~]$ ssh-copy-id testuser@long.tedious.domain.name                              ",{}]],"13":[["/bin/ssh-copy-id: INFO: attempting to log in with the new key(s), to filter out any that ",{}]],"14":[["are already installed                                                                    ",{}]],"15":[["/bin/ssh-copy-id: INFO: 1 key(s) remain to be installed -- if you are prompted now it is ",{}]],"16":[["to install the new keys                                                                  ",{}]],"17":[["testuser@long.tedious.domain.name's password:                                            ",{}]],"18":[["                                                                                         ",{}]],"19":[["Number of key(s) added: 1                                                                ",{}]],"20":[["                                                                                         ",{}]],"21":[["Now try logging into the machine, with:   \"ssh 'testuser@long.tedious.domain.name'\"      ",{}]],"22":[["and check to make sure that only the key(s) you wanted were added.                       ",{}]],"23":[["                                                                                         ",{}]],"24":[["[tpa@zapt ~]$ ssh testuser@long.tedious.domain.name                                      ",{}]],"25":[["[testuser@dogwood00 ~]$ logout                                                           ",{}]],"26":[["Connection to long.tedious.domain.name closed.                                           ",{}]],"27":[["[tpa@zapt ~]$ vim .ssh/config                                                            ",{}]],"28":[["                                                                                         ",{}]]},"cursor":{"x":0,"visible":true}}],[0.000428,{"lines":{"28":[["[tpa@zapt ~]$                                                                            ",{}]]},"cursor":{"x":14}}],[1.149438,{"lines":{"28":[["[tpa@zapt ~]$ c                                                                          ",{}]]},"cursor":{"x":15}}],[0.095995,{"lines":{"28":[["[tpa@zapt ~]$ ch                                                                         ",{}]]},"cursor":{"x":16}}],[0.191533,{"lines":{"28":[["[tpa@zapt ~]$ chm                                                                        ",{}]]},"cursor":{"x":17}}],[0.079987,{"lines":{"28":[["[tpa@zapt ~]$ chmo                                                                       ",{}]]},"cursor":{"x":18}}],[0.112645,{"lines":{"28":[["[tpa@zapt ~]$ chmod                                                                      ",{}]]},"cursor":{"x":19}}],[0.09537900000000001,{"cursor":{"x":20}}],[0.240247,{"lines":{"28":[["[tpa@zapt ~]$ chmod g                                                                    ",{}]]},"cursor":{"x":21}}],[0.11158,{"lines":{"28":[["[tpa@zapt ~]$ chmod go                                                                   ",{}]]},"cursor":{"x":22}}],[0.207993,{"lines":{"28":[["[tpa@zapt ~]$ chmod go-                                                                  ",{}]]},"cursor":{"x":23}}],[0.144083,{"lines":{"28":[["[tpa@zapt ~]$ chmod go-r                                                                 ",{}]]},"cursor":{"x":24}}],[0.736559,{"lines":{"28":[["[tpa@zapt ~]$ chmod go-rw                                                                ",{}]]},"cursor":{"x":25}}],[0.207538,{"lines":{"28":[["[tpa@zapt ~]$ chmod go-rwx                                                               ",{}]]},"cursor":{"x":26}}],[0.6241409999999999,{"cursor":{"x":27}}],[0.5603050000000001,{"lines":{"28":[["[tpa@zapt ~]$ chmod go-rwx .                                                             ",{}]]},"cursor":{"x":28}}],[0.06402099999999999,{"lines":{"28":[["[tpa@zapt ~]$ chmod go-rwx .s                                                            ",{}]]},"cursor":{"x":29}}],[0.247474,{"lines":{"28":[["[tpa@zapt ~]$ chmod go-rwx .ssh/                                                         ",{}]]},"cursor":{"x":32}}],[0.280517,{"lines":{"28":[["[tpa@zapt ~]$ chmod go-rwx .ssh/c                                                        ",{}]]},"cursor":{"x":33}}],[0.112014,{"lines":{"28":[["[tpa@zapt ~]$ chmod go-rwx .ssh/co                                                       ",{}]]},"cursor":{"x":34}}],[0.098105,{"lines":{"28":[["[tpa@zapt ~]$ chmod go-rwx .ssh/config                                                   ",{}]]},"cursor":{"x":39}}],[0.669505,{"lines":{"0":[["+--[ RSA 2048]----+                                                                      ",{}]],"1":[["|            E.   |                                                                      ",{}]],"2":[["|          . . .  |                                                                      ",{}]],"3":[["|         . + o   |                                                                      ",{}]],"4":[["|     .    o =    |                                                                      ",{}]],"5":[["|    . . S  + .   |                                                                      ",{}]],"6":[["|     . o  . +    |                                                                      ",{}]],"7":[["|      o= o . +   |                                                                      ",{}]],"8":[["|      ooO   . .  |                                                                      ",{}]],"9":[["|      .=o.       |                                                                      ",{}]],"10":[["+-----------------+                                                                      ",{}]],"11":[["[tpa@zapt ~]$ ssh-copy-id testuser@long.tedious.domain.name                              ",{}]],"12":[["/bin/ssh-copy-id: INFO: attempting to log in with the new key(s), to filter out any that ",{}]],"13":[["are already installed                                                                    ",{}]],"14":[["/bin/ssh-copy-id: INFO: 1 key(s) remain to be installed -- if you are prompted now it is ",{}]],"15":[["to install the new keys                                                                  ",{}]],"16":[["testuser@long.tedious.domain.name's password:                                            ",{}]],"17":[["                                                                                         ",{}]],"18":[["Number of key(s) added: 1                                                                ",{}]],"19":[["                                                                                         ",{}]],"20":[["Now try logging into the machine, with:   \"ssh 'testuser@long.tedious.domain.name'\"      ",{}]],"21":[["and check to make sure that only the key(s) you wanted were added.                       ",{}]],"22":[["                                                                                         ",{}]],"23":[["[tpa@zapt ~]$ ssh testuser@long.tedious.domain.name                                      ",{}]],"24":[["[testuser@dogwood00 ~]$ logout                                                           ",{}]],"25":[["Connection to long.tedious.domain.name closed.                                           ",{}]],"26":[["[tpa@zapt ~]$ vim .ssh/config                                                            ",{}]],"27":[["[tpa@zapt ~]$ chmod go-rwx .ssh/config                                                   ",{}]],"28":[["                                                                                         ",{}]]},"cursor":{"x":0}}],[0.002395,{"lines":{"28":[["[tpa@zapt ~]$                                                                            ",{}]]},"cursor":{"x":14}}],[0.846027,{"lines":{"28":[["[tpa@zapt ~]$ s                                                                          ",{}]]},"cursor":{"x":15}}],[0.127978,{"lines":{"28":[["[tpa@zapt ~]$ ss                                                                         ",{}]]},"cursor":{"x":16}}],[0.047666,{"lines":{"28":[["[tpa@zapt ~]$ ssh                                                                        ",{}]]},"cursor":{"x":17}}],[0.08046200000000001,{"cursor":{"x":18}}],[0.079318,{"lines":{"28":[["[tpa@zapt ~]$ ssh d                                                                      ",{}]]},"cursor":{"x":19}}],[0.063958,{"lines":{"28":[["[tpa@zapt ~]$ ssh do                                                                     ",{}]]},"cursor":{"x":20}}],[0.096719,{"lines":{"28":[["[tpa@zapt ~]$ ssh dog                                                                    ",{}]]},"cursor":{"x":21}}],[0.080023,{"lines":{"28":[["[tpa@zapt ~]$ ssh dogw                                                                   ",{}]]},"cursor":{"x":22}}],[0.06331000000000001,{"lines":{"28":[["[tpa@zapt ~]$ ssh dogwo                                                                  ",{}]]},"cursor":{"x":23}}],[0.127925,{"lines":{"28":[["[tpa@zapt ~]$ ssh dogwoo                                                                 ",{}]]},"cursor":{"x":24}}],[0.08068500000000001,{"lines":{"28":[["[tpa@zapt ~]$ ssh dogwood                                                                ",{}]]},"cursor":{"x":25}}],[0.191418,{"lines":{"28":[["[tpa@zapt ~]$ ssh dogwood0                                                               ",{}]]},"cursor":{"x":26}}],[0.128023,{"lines":{"28":[["[tpa@zapt ~]$ ssh dogwood00                                                              ",{}]]},"cursor":{"x":27}}],[0.512186,{"lines":{"0":[["|            E.   |                                                                      ",{}]],"1":[["|          . . .  |                                                                      ",{}]],"2":[["|         . + o   |                                                                      ",{}]],"3":[["|     .    o =    |                                                                      ",{}]],"4":[["|    . . S  + .   |                                                                      ",{}]],"5":[["|     . o  . +    |                                                                      ",{}]],"6":[["|      o= o . +   |                                                                      ",{}]],"7":[["|      ooO   . .  |                                                                      ",{}]],"8":[["|      .=o.       |                                                                      ",{}]],"9":[["+-----------------+                                                                      ",{}]],"10":[["[tpa@zapt ~]$ ssh-copy-id testuser@long.tedious.domain.name                              ",{}]],"11":[["/bin/ssh-copy-id: INFO: attempting to log in with the new key(s), to filter out any that ",{}]],"12":[["are already installed                                                                    ",{}]],"13":[["/bin/ssh-copy-id: INFO: 1 key(s) remain to be installed -- if you are prompted now it is ",{}]],"14":[["to install the new keys                                                                  ",{}]],"15":[["testuser@long.tedious.domain.name's password:                                            ",{}]],"16":[["                                                                                         ",{}]],"17":[["Number of key(s) added: 1                                                                ",{}]],"18":[["                                                                                         ",{}]],"19":[["Now try logging into the machine, with:   \"ssh 'testuser@long.tedious.domain.name'\"      ",{}]],"20":[["and check to make sure that only the key(s) you wanted were added.                       ",{}]],"21":[["                                                                                         ",{}]],"22":[["[tpa@zapt ~]$ ssh testuser@long.tedious.domain.name                                      ",{}]],"23":[["[testuser@dogwood00 ~]$ logout                                                           ",{}]],"24":[["Connection to long.tedious.domain.name closed.                                           ",{}]],"25":[["[tpa@zapt ~]$ vim .ssh/config                                                            ",{}]],"26":[["[tpa@zapt ~]$ chmod go-rwx .ssh/config                                                   ",{}]],"27":[["[tpa@zapt ~]$ ssh dogwood00                                                              ",{}]],"28":[["                                                                                         ",{}]]},"cursor":{"x":0}}],[2.364627,{}],[0.001851,{"lines":{"28":[["[testuser@dogwood00 ~]$                                                                  ",{}]]},"cursor":{"x":24}}],[2.024081,{"lines":{"0":[["|          . . .  |                                                                      ",{}]],"1":[["|         . + o   |                                                                      ",{}]],"2":[["|     .    o =    |                                                                      ",{}]],"3":[["|    . . S  + .   |                                                                      ",{}]],"4":[["|     . o  . +    |                                                                      ",{}]],"5":[["|      o= o . +   |                                                                      ",{}]],"6":[["|      ooO   . .  |                                                                      ",{}]],"7":[["|      .=o.       |                                                                      ",{}]],"8":[["+-----------------+                                                                      ",{}]],"9":[["[tpa@zapt ~]$ ssh-copy-id testuser@long.tedious.domain.name                              ",{}]],"10":[["/bin/ssh-copy-id: INFO: attempting to log in with the new key(s), to filter out any that ",{}]],"11":[["are already installed                                                                    ",{}]],"12":[["/bin/ssh-copy-id: INFO: 1 key(s) remain to be installed -- if you are prompted now it is ",{}]],"13":[["to install the new keys                                                                  ",{}]],"14":[["testuser@long.tedious.domain.name's password:                                            ",{}]],"15":[["                                                                                         ",{}]],"16":[["Number of key(s) added: 1                                                                ",{}]],"17":[["                                                                                         ",{}]],"18":[["Now try logging into the machine, with:   \"ssh 'testuser@long.tedious.domain.name'\"      ",{}]],"19":[["and check to make sure that only the key(s) you wanted were added.                       ",{}]],"20":[["                                                                                         ",{}]],"21":[["[tpa@zapt ~]$ ssh testuser@long.tedious.domain.name                                      ",{}]],"22":[["[testuser@dogwood00 ~]$ logout                                                           ",{}]],"23":[["Connection to long.tedious.domain.name closed.                                           ",{}]],"24":[["[tpa@zapt ~]$ vim .ssh/config                                                            ",{}]],"25":[["[tpa@zapt ~]$ chmod go-rwx .ssh/config                                                   ",{}]],"26":[["[tpa@zapt ~]$ ssh dogwood00                                                              ",{}]],"27":[["[testuser@dogwood00 ~]$ logout                                                           ",{}]],"28":[["                                                                                         ",{}]]},"cursor":{"x":0}}],[0.001611,{"lines":{"0":[["|         . + o   |                                                                      ",{}]],"1":[["|     .    o =    |                                                                      ",{}]],"2":[["|    . . S  + .   |                                                                      ",{}]],"3":[["|     . o  . +    |                                                                      ",{}]],"4":[["|      o= o . +   |                                                                      ",{}]],"5":[["|      ooO   . .  |                                                                      ",{}]],"6":[["|      .=o.       |                                                                      ",{}]],"7":[["+-----------------+                                                                      ",{}]],"8":[["[tpa@zapt ~]$ ssh-copy-id testuser@long.tedious.domain.name                              ",{}]],"9":[["/bin/ssh-copy-id: INFO: attempting to log in with the new key(s), to filter out any that ",{}]],"10":[["are already installed                                                                    ",{}]],"11":[["/bin/ssh-copy-id: INFO: 1 key(s) remain to be installed -- if you are prompted now it is ",{}]],"12":[["to install the new keys                                                                  ",{}]],"13":[["testuser@long.tedious.domain.name's password:                                            ",{}]],"14":[["                                                                                         ",{}]],"15":[["Number of key(s) added: 1                                                                ",{}]],"16":[["                                                                                         ",{}]],"17":[["Now try logging into the machine, with:   \"ssh 'testuser@long.tedious.domain.name'\"      ",{}]],"18":[["and check to make sure that only the key(s) you wanted were added.                       ",{}]],"19":[["                                                                                         ",{}]],"20":[["[tpa@zapt ~]$ ssh testuser@long.tedious.domain.name                                      ",{}]],"21":[["[testuser@dogwood00 ~]$ logout                                                           ",{}]],"22":[["Connection to long.tedious.domain.name closed.                                           ",{}]],"23":[["[tpa@zapt ~]$ vim .ssh/config                                                            ",{}]],"24":[["[tpa@zapt ~]$ chmod go-rwx .ssh/config                                                   ",{}]],"25":[["[tpa@zapt ~]$ ssh dogwood00                                                              ",{}]],"26":[["[testuser@dogwood00 ~]$ logout                                                           ",{}]],"27":[["Connection to long.tedious.domain.name closed.                                           ",{}]],"28":[["[tpa@zapt ~]$                                                                            ",{}]]},"cursor":{"x":14}}],[0.344201,{"lines":{"28":[["[tpa@zapt ~]$ s                                                                          ",{}]]},"cursor":{"x":15}}],[0.127977,{"lines":{"28":[["[tpa@zapt ~]$ ss                                                                         ",{}]]},"cursor":{"x":16}}],[0.047024,{"lines":{"28":[["[tpa@zapt ~]$ ssh                                                                        ",{}]]},"cursor":{"x":17}}],[0.095789,{"cursor":{"x":18}}],[0.064415,{"lines":{"28":[["[tpa@zapt ~]$ ssh d                                                                      ",{}]]},"cursor":{"x":19}}],[0.064138,{"lines":{"28":[["[tpa@zapt ~]$ ssh do                                                                     ",{}]]},"cursor":{"x":20}}],[0.08067199999999999,{"lines":{"28":[["[tpa@zapt ~]$ ssh dog                                                                    ",{}]]},"cursor":{"x":21}}],[0.079442,{"lines":{"28":[["[tpa@zapt ~]$ ssh dogw                                                                   ",{}]]},"cursor":{"x":22}}],[0.047948,{"lines":{"28":[["[tpa@zapt ~]$ ssh dogwo                                                                  ",{}]]},"cursor":{"x":23}}],[0.144019,{"lines":{"28":[["[tpa@zapt ~]$ ssh dogwoo                                                                 ",{}]]},"cursor":{"x":24}}],[0.112044,{"lines":{"28":[["[tpa@zapt ~]$ ssh dogwood                                                                ",{}]]},"cursor":{"x":25}}],[0.272583,{"lines":{"28":[["[tpa@zapt ~]$ ssh dogwood0                                                               ",{}]]},"cursor":{"x":26}}],[0.127984,{"lines":{"28":[["[tpa@zapt ~]$ ssh dogwood01                                                              ",{}]]},"cursor":{"x":27}}],[0.832462,{"lines":{"0":[["|     .    o =    |                                                                      ",{}]],"1":[["|    . . S  + .   |                                                                      ",{}]],"2":[["|     . o  . +    |                                                                      ",{}]],"3":[["|      o= o . +   |                                                                      ",{}]],"4":[["|      ooO   . .  |                                                                      ",{}]],"5":[["|      .=o.       |                                                                      ",{}]],"6":[["+-----------------+                                                                      ",{}]],"7":[["[tpa@zapt ~]$ ssh-copy-id testuser@long.tedious.domain.name                              ",{}]],"8":[["/bin/ssh-copy-id: INFO: attempting to log in with the new key(s), to filter out any that ",{}]],"9":[["are already installed                                                                    ",{}]],"10":[["/bin/ssh-copy-id: INFO: 1 key(s) remain to be installed -- if you are prompted now it is ",{}]],"11":[["to install the new keys                                                                  ",{}]],"12":[["testuser@long.tedious.domain.name's password:                                            ",{}]],"13":[["                                                                                         ",{}]],"14":[["Number of key(s) added: 1                                                                ",{}]],"15":[["                                                                                         ",{}]],"16":[["Now try logging into the machine, with:   \"ssh 'testuser@long.tedious.domain.name'\"      ",{}]],"17":[["and check to make sure that only the key(s) you wanted were added.                       ",{}]],"18":[["                                                                                         ",{}]],"19":[["[tpa@zapt ~]$ ssh testuser@long.tedious.domain.name                                      ",{}]],"20":[["[testuser@dogwood00 ~]$ logout                                                           ",{}]],"21":[["Connection to long.tedious.domain.name closed.                                           ",{}]],"22":[["[tpa@zapt ~]$ vim .ssh/config                                                            ",{}]],"23":[["[tpa@zapt ~]$ chmod go-rwx .ssh/config                                                   ",{}]],"24":[["[tpa@zapt ~]$ ssh dogwood00                                                              ",{}]],"25":[["[testuser@dogwood00 ~]$ logout                                                           ",{}]],"26":[["Connection to long.tedious.domain.name closed.                                           ",{}]],"27":[["[tpa@zapt ~]$ ssh dogwood01                                                              ",{}]],"28":[["                                                                                         ",{}]]},"cursor":{"x":0}}],[3.241997,{"lines":{"28":[["[testuser@dogwood01 ~]$                                                                  ",{}]]},"cursor":{"x":24}}],[2.38849,{"lines":{"0":[["|      o= o . +   |                                                                      ",{}]],"1":[["|      ooO   . .  |                                                                      ",{}]],"2":[["|      .=o.       |                                                                      ",{}]],"3":[["+-----------------+                                                                      ",{}]],"4":[["[tpa@zapt ~]$ ssh-copy-id testuser@long.tedious.domain.name                              ",{}]],"5":[["/bin/ssh-copy-id: INFO: attempting to log in with the new key(s), to filter out any that ",{}]],"6":[["are already installed                                                                    ",{}]],"7":[["/bin/ssh-copy-id: INFO: 1 key(s) remain to be installed -- if you are prompted now it is ",{}]],"8":[["to install the new keys                                                                  ",{}]],"9":[["testuser@long.tedious.domain.name's password:                                            ",{}]],"10":[["                                                                                         ",{}]],"11":[["Number of key(s) added: 1                                                                ",{}]],"12":[["                                                                                         ",{}]],"13":[["Now try logging into the machine, with:   \"ssh 'testuser@long.tedious.domain.name'\"      ",{}]],"14":[["and check to make sure that only the key(s) you wanted were added.                       ",{}]],"16":[["[tpa@zapt ~]$ ssh testuser@long.tedious.domain.name                                      ",{}]],"17":[["[testuser@dogwood00 ~]$ logout                                                           ",{}]],"18":[["Connection to long.tedious.domain.name closed.                                           ",{}]],"19":[["[tpa@zapt ~]$ vim .ssh/config                                                            ",{}]],"20":[["[tpa@zapt ~]$ chmod go-rwx .ssh/config                                                   ",{}]],"21":[["[tpa@zapt ~]$ ssh dogwood00                                                              ",{}]],"22":[["[testuser@dogwood00 ~]$ logout                                                           ",{}]],"23":[["Connection to long.tedious.domain.name closed.                                           ",{}]],"24":[["[tpa@zapt ~]$ ssh dogwood01                                                              ",{}]],"25":[["[testuser@dogwood01 ~]$ logout                                                           ",{}]],"26":[["Connection to dogwood01 closed.                                                          ",{}]],"27":[["Killed by signal 1.                                                                      ",{}]],"28":[["                                                                                         ",{}]]},"cursor":{"x":0}}],[0.000428,{"lines":{"28":[["[tpa@zapt ~]$                                                                            ",{}]]},"cursor":{"x":14}}],[2.063901,{"lines":{"0":[["|      ooO   . .  |                                                                      ",{}]],"1":[["|      .=o.       |                                                                      ",{}]],"2":[["+-----------------+                                                                      ",{}]],"3":[["[tpa@zapt ~]$ ssh-copy-id testuser@long.tedious.domain.name                              ",{}]],"4":[["/bin/ssh-copy-id: INFO: attempting to log in with the new key(s), to filter out any that ",{}]],"5":[["are already installed                                                                    ",{}]],"6":[["/bin/ssh-copy-id: INFO: 1 key(s) remain to be installed -- if you are prompted now it is ",{}]],"7":[["to install the new keys                                                                  ",{}]],"8":[["testuser@long.tedious.domain.name's password:                                            ",{}]],"9":[["                                                                                         ",{}]],"10":[["Number of key(s) added: 1                                                                ",{}]],"11":[["                                                                                         ",{}]],"12":[["Now try logging into the machine, with:   \"ssh 'testuser@long.tedious.domain.name'\"      ",{}]],"13":[["and check to make sure that only the key(s) you wanted were added.                       ",{}]],"14":[["                                                                                         ",{}]],"15":[["[tpa@zapt ~]$ ssh testuser@long.tedious.domain.name                                      ",{}]],"16":[["[testuser@dogwood00 ~]$ logout                                                           ",{}]],"17":[["Connection to long.tedious.domain.name closed.                                           ",{}]],"18":[["[tpa@zapt ~]$ vim .ssh/config                                                            ",{}]],"19":[["[tpa@zapt ~]$ chmod go-rwx .ssh/config                                                   ",{}]],"20":[["[tpa@zapt ~]$ ssh dogwood00                                                              ",{}]],"21":[["[testuser@dogwood00 ~]$ logout                                                           ",{}]],"22":[["Connection to long.tedious.domain.name closed.                                           ",{}]],"23":[["[tpa@zapt ~]$ ssh dogwood01                                                              ",{}]],"24":[["[testuser@dogwood01 ~]$ logout                                                           ",{}]],"25":[["Connection to dogwood01 closed.                                                          ",{}]],"26":[["Killed by signal 1.                                                                      ",{}]],"27":[["[tpa@zapt ~]$ exit                                                                       ",{}]],"28":[["                                                                                         ",{}]]},"cursor":{"x":0}}]]