[[0.00712,{"lines":{"0":[["$                                                                                                                                                                                                             ",{}]],"1":[["                                                                                                                                                                                                              ",{}]],"2":[["                                                                                                                                                                                                              ",{}]],"3":[["                                                                                                                                                                                                              ",{}]],"4":[["                                                                                                                                                                                                              ",{}]],"5":[["                                                                                                                                                                                                              ",{}]],"6":[["                                                                                                                                                                                                              ",{}]],"7":[["                                                                                                                                                                                                              ",{}]],"8":[["                                                                                                                                                                                                              ",{}]],"9":[["                                                                                                                                                                                                              ",{}]],"10":[["                                                                                                                                                                                                              ",{}]],"11":[["                                                                                                                                                                                                              ",{}]],"12":[["                                                                                                                                                                                                              ",{}]],"13":[["                                                                                                                                                                                                              ",{}]],"14":[["                                                                                                                                                                                                              ",{}]],"15":[["                                                                                                                                                                                                              ",{}]],"16":[["                                                                                                                                                                                                              ",{}]],"17":[["                                                                                                                                                                                                              ",{}]],"18":[["                                                                                                                                                                                                              ",{}]],"19":[["                                                                                                                                                                                                              ",{}]],"20":[["                                                                                                                                                                                                              ",{}]],"21":[["                                                                                                                                                                                                              ",{}]],"22":[["                                                                                                                                                                                                              ",{}]],"23":[["                                                                                                                                                                                                              ",{}]],"24":[["                                                                                                                                                                                                              ",{}]],"25":[["                                                                                                                                                                                                              ",{}]],"26":[["                                                                                                                                                                                                              ",{}]],"27":[["                                                                                                                                                                                                              ",{}]],"28":[["                                                                                                                                                                                                              ",{}]],"29":[["                                                                                                                                                                                                              ",{}]],"30":[["                                                                                                                                                                                                              ",{}]],"31":[["                                                                                                                                                                                                              ",{}]],"32":[["                                                                                                                                                                                                              ",{}]],"33":[["                                                                                                                                                                                                              ",{}]],"34":[["                                                                                                                                                                                                              ",{}]],"35":[["                                                                                                                                                                                                              ",{}]],"36":[["                                                                                                                                                                                                              ",{}]],"37":[["                                                                                                                                                                                                              ",{}]],"38":[["                                                                                                                                                                                                              ",{}]],"39":[["                                                                                                                                                                                                              ",{}]],"40":[["                                                                                                                                                                                                              ",{}]],"41":[["                                                                                                                                                                                                              ",{}]],"42":[["                                                                                                                                                                                                              ",{}]],"43":[["                                                                                                                                                                                                              ",{}]],"44":[["                                                                                                                                                                                                              ",{}]],"45":[["                                                                                                                                                                                                              ",{}]],"46":[["                                                                                                                                                                                                              ",{}]],"47":[["                                                                                                                                                                                                              ",{}]],"48":[["                                                                                                                                                                                                              ",{}]]},"cursor":{"x":2,"y":0,"visible":true}}],[1.876784,{"lines":{"0":[["$ w                                                                                                                                                                                                           ",{}]]},"cursor":{"x":3}}],[0.231812,{"lines":{"0":[["$ wa                                                                                                                                                                                                          ",{}]]},"cursor":{"x":4}}],[0.120024,{"lines":{"0":[["$ wat                                                                                                                                                                                                         ",{}]]},"cursor":{"x":5}}],[0.240068,{"lines":{"0":[["$ watc                                                                                                                                                                                                        ",{}]]},"cursor":{"x":6}}],[0.103981,{"lines":{"0":[["$ watch                                                                                                                                                                                                       ",{}]]},"cursor":{"x":7}}],[0.072168,{"cursor":{"x":8}}],[0.104317,{"lines":{"0":[["$ watch d                                                                                                                                                                                                     ",{}]]},"cursor":{"x":9}}],[0.119577,{"lines":{"0":[["$ watch da                                                                                                                                                                                                    ",{}]]},"cursor":{"x":10}}],[0.143815,{"lines":{"0":[["$ watch dat                                                                                                                                                                                                   ",{}]]},"cursor":{"x":11}}],[0.09617199999999999,{"lines":{"0":[["$ watch date                                                                                                                                                                                                  ",{}]]},"cursor":{"x":12}}],[0.17678,{"cursor":{"x":0,"y":1}}],[0.029447,{"lines":{"0":[["Every 2.0s: date                                                                                                                                                                      Thu Apr 16 13:23:17 2015",{}]],"2":[["Thu Apr 16 13:23:17 EDT 2015                                                                                                                                                                                  ",{}]]},"cursor":{"x":205,"y":48}}],[2.006809,{"lines":{"0":[["Every 2.0s: date                                                                                                                                                                      Thu Apr 16 13:23:19 2015",{}]],"2":[["Thu Apr 16 13:23:19 EDT 2015                                                                                                                                                                                  ",{}]]}}],[1.795759,{"lines":{"0":[["$ watch date                                                                                                                                                                                                  ",{}]],"1":[["$                                                                                                                                                                                                             ",{}]],"2":[["                                                                                                                                                                                                              ",{}]]},"cursor":{"x":2,"y":1}}],[1.216008,{"lines":{"1":[["$ exit                                                                                                                                                                                                        ",{}]]},"cursor":{"x":0,"y":2}}]]